fiscaliza/__init__.py
fiscaliza/attrs.py
fiscaliza/constants.py
fiscaliza/datatypes.py
fiscaliza/main.py
fiscaliza-1.0.2.dist-info/METADATA
fiscaliza-1.0.2.dist-info/WHEEL
fiscaliza-1.0.2.dist-info/entry_points.txt
fiscaliza-1.0.2.dist-info/licenses/LICENSE
fiscaliza-1.0.2.dist-info/RECORD
