Metadata-Version: 2.3
Name: fiscaliza
Version: 1.0.2
Summary: Implementação de API python a instância do Redmine da Anatel: Fiscaliza
Author-email: "Ronaldo S.A. Batista" <ronaldokun@gmail.com>
Requires-Python: <3.12,>=3.11
Requires-Dist: certifi==2024.6.2
Requires-Dist: fastcore>=1.5.46
Requires-Dist: python-dotenv>=1.0.1
Requires-Dist: python-redmine==2.4.0
Requires-Dist: unidecode>=1.3.8
Requires-Dist: urllib3==2.2.2
